[
    null,
    {
        "id": 1,
        "autoRemovalTiming": 0,
        "chanceByDamage": 100,
        "iconIndex": 1,
        "maxTurns": 1,
        "message1": "は倒れた！",
        "message2": "を倒した！",
        "message3": "",
        "message4": "は立ち上がった！",
        "minTurns": 1,
        "motion": 3,
        "name": "戦闘不能",
        "note": "ステート１番はＨＰが０になったときに\n自動的に付加されます。",
        "overlay": 0,
        "priority": 100,
        "releaseByDamage": false,
        "removeAtBattleEnd": false,
        "removeByDamage": false,
        "removeByRestriction": false,
        "removeByWalking": false,
        "restriction": 2,
        "stepsToRemove": 100,
        "traits": [
            {
                "code": 23,
                "dataId": 9,
                "value": 0
            }
        ]
    },
    {
        "id": 2,
        "autoRemovalTiming": 2,
        "chanceByDamage": 100,
        "description": "",
        "iconIndex": 0,
        "maxTurns": 1,
        "message1": "",
        "message2": "",
        "message3": "",
        "message4": "",
        "minTurns": 1,
        "motion": 0,
        "name": "防御",
        "note": "",
        "overlay": 0,
        "priority": 0,
        "removeAtBattleEnd": true,
        "removeByDamage": false,
        "removeByRestriction": true,
        "removeByWalking": false,
        "restriction": 0,
        "stepsToRemove": 100,
        "traits": [
            {
                "code": 62,
                "dataId": 1,
                "value": 0
            }
        ]
    },
    {
        "id": 3,
        "autoRemovalTiming": 0,
        "chanceByDamage": 100,
        "description": "",
        "iconIndex": 0,
        "maxTurns": 1,
        "message1": "",
        "message2": "",
        "message3": "",
        "message4": "",
        "minTurns": 1,
        "motion": 0,
        "name": "不死身",
        "note": "",
        "overlay": 0,
        "priority": 0,
        "removeAtBattleEnd": true,
        "removeByDamage": false,
        "removeByRestriction": false,
        "removeByWalking": false,
        "restriction": 0,
        "stepsToRemove": 100,
        "traits": [
            {
                "code": 14,
                "dataId": 1,
                "value": 0
            }
        ]
    },
    {
        "id": 4,
        "autoRemovalTiming": 0,
        "chanceByDamage": 100,
        "traits": [],
        "iconIndex": 0,
        "maxTurns": 1,
        "message1": "",
        "message2": "",
        "message3": "",
        "message4": "",
        "minTurns": 1,
        "motion": 0,
        "name": "",
        "note": "",
        "overlay": 0,
        "priority": 50,
        "removeAtBattleEnd": false,
        "removeByDamage": false,
        "removeByRestriction": false,
        "removeByWalking": false,
        "restriction": 0,
        "stepsToRemove": 100
    },
    {
        "id": 5,
        "autoRemovalTiming": 0,
        "chanceByDamage": 100,
        "traits": [],
        "iconIndex": 0,
        "maxTurns": 1,
        "message1": "",
        "message2": "",
        "message3": "",
        "message4": "",
        "minTurns": 1,
        "motion": 0,
        "name": "",
        "note": "",
        "overlay": 0,
        "priority": 50,
        "removeAtBattleEnd": false,
        "removeByDamage": false,
        "removeByRestriction": false,
        "removeByWalking": false,
        "restriction": 0,
        "stepsToRemove": 100
    },
    {
        "id": 6,
        "autoRemovalTiming": 2,
        "chanceByDamage": 100,
        "traits": [
            {
                "code": 23,
                "dataId": 0,
                "value": 1.5
            }
        ],
        "iconIndex": 76,
        "maxTurns": 5,
        "message1": "は敵を挑発した！",
        "message2": "",
        "message3": "",
        "message4": "は集中されなくなった！",
        "minTurns": 5,
        "motion": 0,
        "name": "攻撃集中",
        "note": "",
        "overlay": 0,
        "priority": 60,
        "removeAtBattleEnd": true,
        "removeByDamage": false,
        "removeByRestriction": false,
        "removeByWalking": false,
        "restriction": 0,
        "stepsToRemove": 100
    },
    {
        "id": 7,
        "autoRemovalTiming": 1,
        "chanceByDamage": 50,
        "iconIndex": 6,
        "maxTurns": 3,
        "message1": "は混乱した！",
        "message2": "を混乱させた！",
        "message3": "",
        "message4": "は我に返った！",
        "minTurns": 2,
        "motion": 1,
        "name": "混乱",
        "note": "",
        "overlay": 5,
        "priority": 75,
        "releaseByDamage": false,
        "removeAtBattleEnd": true,
        "removeByDamage": false,
        "removeByRestriction": false,
        "removeByWalking": false,
        "restriction": 2,
        "stepsToRemove": 100,
        "traits": []
    },
    {
        "id": 8,
        "autoRemovalTiming": 1,
        "chanceByDamage": 50,
        "iconIndex": 80,
        "maxTurns": 3,
        "message1": "は魅了された！",
        "message2": "を魅了した！",
        "message3": "",
        "message4": "は我に返った！",
        "minTurns": 1,
        "motion": 1,
        "name": "魅了",
        "note": "",
        "overlay": 6,
        "priority": 80,
        "releaseByDamage": false,
        "removeAtBattleEnd": true,
        "removeByDamage": false,
        "removeByRestriction": false,
        "removeByWalking": false,
        "restriction": 3,
        "stepsToRemove": 100,
        "traits": []
    },
    {
        "id": 9,
        "autoRemovalTiming": 1,
        "chanceByDamage": 100,
        "iconIndex": 8,
        "maxTurns": 2,
        "message1": "は眠った！",
        "message2": "を眠らせた！",
        "message3": "は眠っている。",
        "message4": "は目を覚ました！",
        "minTurns": 1,
        "motion": 2,
        "name": "睡眠",
        "note": "",
        "overlay": 7,
        "priority": 88,
        "releaseByDamage": true,
        "removeAtBattleEnd": true,
        "removeByDamage": true,
        "removeByRestriction": false,
        "removeByWalking": false,
        "restriction": 4,
        "stepsToRemove": 100,
        "traits": [
            {
                "code": 22,
                "dataId": 1,
                "value": -1
            }
        ]
    },
    {
        "id": 10,
        "autoRemovalTiming": 0,
        "chanceByDamage": 100,
        "traits": [],
        "iconIndex": 0,
        "maxTurns": 1,
        "message1": "",
        "message2": "",
        "message3": "",
        "message4": "",
        "minTurns": 1,
        "motion": 0,
        "name": "",
        "note": "",
        "overlay": 0,
        "priority": 50,
        "removeAtBattleEnd": false,
        "removeByDamage": false,
        "removeByRestriction": false,
        "removeByWalking": false,
        "restriction": 0,
        "stepsToRemove": 100
    },
    {
        "id": 11,
        "autoRemovalTiming": 2,
        "chanceByDamage": 100,
        "iconIndex": 65,
        "maxTurns": 3,
        "message1": "は凍った！",
        "message2": "は凍った！",
        "message3": "",
        "message4": "の氷がとけた！！",
        "minTurns": 2,
        "motion": 0,
        "overlay": 0,
        "name": "冷凍",
        "note": "",
        "priority": 88,
        "releaseByDamage": false,
        "removeAtBattleEnd": true,
        "removeByDamage": false,
        "removeByRestriction": false,
        "removeByWalking": false,
        "restriction": 4,
        "stepsToRemove": 100,
        "traits": [
            {
                "code": 22,
                "dataId": 1,
                "value": -1
            }
        ]
    },
    {
        "id": 12,
        "autoRemovalTiming": 0,
        "chanceByDamage": 100,
        "iconIndex": 64,
        "maxTurns": 4,
        "message1": "は火傷になった！",
        "message2": "は火傷になった！",
        "message3": "",
        "message4": "の火傷が消えた！",
        "minTurns": 3,
        "motion": 0,
        "overlay": 0,
        "name": "火傷",
        "note": "",
        "priority": 88,
        "releaseByDamage": false,
        "removeAtBattleEnd": true,
        "removeByDamage": false,
        "removeByRestriction": false,
        "removeByWalking": false,
        "restriction": 0,
        "stepsToRemove": 100,
        "traits": [
            {
                "code": 22,
                "dataId": 7,
                "value": -0.05
            }
        ]
    },
    {
        "id": 13,
        "autoRemovalTiming": 0,
        "chanceByDamage": 100,
        "iconIndex": 66,
        "maxTurns": 2,
        "message1": "は麻痺になった！",
        "message2": "は麻痺になった！",
        "message3": "",
        "message4": "の麻痺がなおった！！",
        "minTurns": 1,
        "motion": 0,
        "overlay": 0,
        "name": "麻痺",
        "note": "<numb_rate:30>",
        "priority": 88,
        "releaseByDamage": false,
        "removeAtBattleEnd": true,
        "removeByDamage": false,
        "removeByRestriction": false,
        "removeByWalking": false,
        "restriction": 0,
        "stepsToRemove": 100,
        "traits": []
    },
    {
        "id": 14,
        "autoRemovalTiming": 2,
        "chanceByDamage": 100,
        "iconIndex": 2,
        "maxTurns": 5,
        "message1": "は毒にかかった！",
        "message2": "に毒をかけた！",
        "message3": "",
        "message4": "の毒が消えた！",
        "minTurns": 4,
        "motion": 1,
        "overlay": 1,
        "name": "毒",
        "note": "",
        "priority": 50,
        "releaseByDamage": false,
        "removeAtBattleEnd": true,
        "removeByDamage": false,
        "removeByRestriction": false,
        "removeByWalking": false,
        "restriction": 0,
        "stepsToRemove": 100,
        "traits": [
            {
                "code": 22,
                "dataId": 7,
                "value": -0.08
            }
        ]
    },
    {
        "id": 15,
        "autoRemovalTiming": 2,
        "chanceByDamage": 100,
        "iconIndex": 9,
        "maxTurns": 1,
        "message1": "は怯んだ！",
        "message2": "は怯んだ！",
        "message3": "は怯んでいる……",
        "message4": "は体勢を立て直した！",
        "minTurns": 1,
        "motion": 3,
        "name": "スタン",
        "note": "",
        "overlay": 0,
        "priority": 88,
        "releaseByDamage": true,
        "removeAtBattleEnd": true,
        "removeByDamage": false,
        "removeByRestriction": false,
        "removeByWalking": false,
        "restriction": 4,
        "stepsToRemove": 100,
        "traits": [
            {
                "code": 22,
                "dataId": 1,
                "value": -1
            }
        ]
    },
    {
        "id": 16,
        "autoRemovalTiming": 0,
        "chanceByDamage": 100,
        "traits": [],
        "iconIndex": 0,
        "maxTurns": 1,
        "message1": "",
        "message2": "",
        "message3": "",
        "message4": "",
        "minTurns": 1,
        "motion": 0,
        "name": "",
        "note": "",
        "overlay": 0,
        "priority": 50,
        "removeAtBattleEnd": false,
        "removeByDamage": false,
        "removeByRestriction": false,
        "removeByWalking": false,
        "restriction": 0,
        "stepsToRemove": 100
    },
    {
        "id": 17,
        "autoRemovalTiming": 2,
        "chanceByDamage": 100,
        "traits": [
            {
                "code": 22,
                "dataId": 2,
                "value": 0.5
            }
        ],
        "iconIndex": 78,
        "maxTurns": 5,
        "message1": "の会心率が上がった！",
        "message2": "の会心率が上がった！",
        "message3": "",
        "message4": "の会心率が戻った！",
        "minTurns": 4,
        "motion": 0,
        "name": "会心率上昇",
        "note": "",
        "overlay": 0,
        "priority": 50,
        "removeAtBattleEnd": true,
        "removeByDamage": false,
        "removeByRestriction": false,
        "removeByWalking": false,
        "restriction": 0,
        "stepsToRemove": 100
    },
    {
        "id": 18,
        "autoRemovalTiming": 2,
        "chanceByDamage": 100,
        "traits": [
            {
                "code": 22,
                "dataId": 7,
                "value": 0.1
            }
        ],
        "iconIndex": 84,
        "maxTurns": 5,
        "message1": "は体力を回復するようになった！",
        "message2": "は体力を回復するようになった！",
        "message3": "",
        "message4": "は体力回復の効果は終わった",
        "minTurns": 5,
        "motion": 0,
        "name": "HP自動回復",
        "note": "",
        "overlay": 0,
        "priority": 50,
        "removeAtBattleEnd": true,
        "removeByDamage": false,
        "removeByRestriction": false,
        "removeByWalking": false,
        "restriction": 0,
        "stepsToRemove": 100
    },
    {
        "id": 19,
        "autoRemovalTiming": 2,
        "chanceByDamage": 100,
        "traits": [
            {
                "code": 22,
                "dataId": 8,
                "value": 0.1
            }
        ],
        "iconIndex": 84,
        "maxTurns": 5,
        "message1": "は特攻力を回復するようになった！",
        "message2": "は特攻力を回復するようになった！",
        "message3": "",
        "message4": "は特攻回復の効果は終わった",
        "minTurns": 5,
        "motion": 0,
        "name": "MP自動回復",
        "note": "",
        "overlay": 0,
        "priority": 50,
        "removeAtBattleEnd": true,
        "removeByDamage": false,
        "removeByRestriction": false,
        "removeByWalking": false,
        "restriction": 0,
        "stepsToRemove": 100
    },
    {
        "id": 20,
        "autoRemovalTiming": 2,
        "chanceByDamage": 100,
        "traits": [
            {
                "code": 14,
                "dataId": 12,
                "value": 1
            },
            {
                "code": 14,
                "dataId": 14,
                "value": 1
            },
            {
                "code": 14,
                "dataId": 13,
                "value": 1
            },
            {
                "code": 14,
                "dataId": 11,
                "value": 1
            },
            {
                "code": 14,
                "dataId": 9,
                "value": 1
            },
            {
                "code": 14,
                "dataId": 7,
                "value": 1
            },
            {
                "code": 14,
                "dataId": 8,
                "value": 1
            }
        ],
        "iconIndex": 128,
        "maxTurns": 5,
        "message1": "は状態異常無効になった！",
        "message2": "は状態異常無効になった！",
        "message3": "",
        "message4": "の状態異常無効がとけた！",
        "minTurns": 5,
        "motion": 0,
        "name": "状態異常無効",
        "note": "",
        "overlay": 0,
        "priority": 50,
        "removeAtBattleEnd": true,
        "removeByDamage": false,
        "removeByRestriction": false,
        "removeByWalking": false,
        "restriction": 0,
        "stepsToRemove": 100
    },
    {
        "id": 21,
        "autoRemovalTiming": 0,
        "chanceByDamage": 100,
        "traits": [
            {
                "code": 61,
                "dataId": 0,
                "value": 1
            }
        ],
        "iconIndex": 89,
        "maxTurns": 3,
        "message1": "の行動回数が増えた！",
        "message2": "の行動回数が増えた！",
        "message3": "",
        "message4": "の行動回数増加が終わった！",
        "minTurns": 3,
        "motion": 0,
        "name": "行動回数追加",
        "note": "",
        "overlay": 0,
        "priority": 50,
        "removeAtBattleEnd": true,
        "removeByDamage": false,
        "removeByRestriction": false,
        "removeByWalking": false,
        "restriction": 0,
        "stepsToRemove": 100
    },
    {
        "id": 22,
        "autoRemovalTiming": 2,
        "chanceByDamage": 100,
        "iconIndex": 77,
        "maxTurns": 5,
        "message1": "はスタンを受けなくなった！",
        "message2": "はスタンを受けなくなった！",
        "message3": "",
        "message4": "はスタン無効は終わった",
        "minTurns": 5,
        "motion": 0,
        "name": "スタン無効",
        "note": "",
        "overlay": 0,
        "priority": 88,
        "releaseByDamage": true,
        "removeAtBattleEnd": true,
        "removeByDamage": false,
        "removeByRestriction": false,
        "removeByWalking": false,
        "restriction": 0,
        "stepsToRemove": 100,
        "traits": [
            {
                "code": 14,
                "dataId": 16,
                "value": 1
            }
        ]
    },
    {
        "id": 23,
        "autoRemovalTiming": 0,
        "chanceByDamage": 100,
        "traits": [
            {
                "code": 23,
                "dataId": 0,
                "value": 1.6
            },
            {
                "code": 21,
                "dataId": 3,
                "value": 0.8
            }
        ],
        "iconIndex": 23,
        "maxTurns": 1,
        "message1": "はムラムラ状態になった！",
        "message2": "はムラムラ状態になった！",
        "message3": "",
        "message4": "は冷静さを取り戻した！",
        "minTurns": 1,
        "motion": 0,
        "name": "ムラムラ",
        "note": "",
        "overlay": 0,
        "priority": 60,
        "removeAtBattleEnd": false,
        "removeByDamage": false,
        "removeByRestriction": false,
        "removeByWalking": false,
        "restriction": 0,
        "stepsToRemove": 100
    },
    {
        "id": 24,
        "autoRemovalTiming": 2,
        "chanceByDamage": 100,
        "iconIndex": 85,
        "maxTurns": 5,
        "message1": "は魅了を受けなくなった！",
        "message2": "は魅了を受けなくなった！",
        "message3": "",
        "message4": "の魅了無効はなくなった！",
        "minTurns": 5,
        "motion": 0,
        "name": "魅了無効",
        "note": "",
        "overlay": 0,
        "priority": 88,
        "releaseByDamage": true,
        "removeAtBattleEnd": true,
        "removeByDamage": false,
        "removeByRestriction": false,
        "removeByWalking": false,
        "restriction": 0,
        "stepsToRemove": 100,
        "traits": [
            {
                "code": 14,
                "dataId": 8,
                "value": 1
            }
        ]
    },
    {
        "id": 25,
        "autoRemovalTiming": 0,
        "chanceByDamage": 100,
        "traits": [],
        "iconIndex": 0,
        "maxTurns": 1,
        "message1": "",
        "message2": "",
        "message3": "",
        "message4": "",
        "minTurns": 1,
        "motion": 0,
        "name": "",
        "note": "",
        "overlay": 0,
        "priority": 50,
        "removeAtBattleEnd": false,
        "removeByDamage": false,
        "removeByRestriction": false,
        "removeByWalking": false,
        "restriction": 0,
        "stepsToRemove": 100
    },
    {
        "id": 26,
        "autoRemovalTiming": 2,
        "chanceByDamage": 100,
        "traits": [
            {
                "code": 22,
                "dataId": 2,
                "value": 1
            }
        ],
        "iconIndex": 78,
        "maxTurns": 3,
        "message1": "は確定で会心するようになった",
        "message2": "は確定で会心するようになった",
        "message3": "",
        "message4": "の確定会心は終わった",
        "minTurns": 3,
        "motion": 0,
        "name": "確定会心",
        "note": "",
        "overlay": 0,
        "priority": 50,
        "removeAtBattleEnd": true,
        "removeByDamage": false,
        "removeByRestriction": false,
        "removeByWalking": false,
        "restriction": 0,
        "stepsToRemove": 100
    },
    {
        "id": 27,
        "autoRemovalTiming": 0,
        "chanceByDamage": 100,
        "iconIndex": 18,
        "maxTurns": 1,
        "message1": "は呪いをかけられた",
        "message2": "は呪いをかけられた",
        "message3": "",
        "message4": "は呪いが解除された",
        "minTurns": 2,
        "motion": 0,
        "name": "呪い",
        "note": "",
        "overlay": 0,
        "priority": 88,
        "releaseByDamage": true,
        "removeAtBattleEnd": true,
        "removeByDamage": false,
        "removeByRestriction": false,
        "removeByWalking": false,
        "restriction": 0,
        "stepsToRemove": 100,
        "traits": [
            {
                "code": 22,
                "dataId": 7,
                "value": -0.5
            }
        ]
    },
    {
        "id": 28,
        "autoRemovalTiming": 0,
        "chanceByDamage": 100,
        "traits": [],
        "iconIndex": 0,
        "maxTurns": 1,
        "message1": "",
        "message2": "",
        "message3": "",
        "message4": "",
        "minTurns": 1,
        "motion": 0,
        "name": "",
        "note": "",
        "overlay": 0,
        "priority": 50,
        "removeAtBattleEnd": false,
        "removeByDamage": false,
        "removeByRestriction": false,
        "removeByWalking": false,
        "restriction": 0,
        "stepsToRemove": 100
    },
    {
        "id": 29,
        "autoRemovalTiming": 2,
        "chanceByDamage": 100,
        "traits": [
            {
                "code": 22,
                "dataId": 5,
                "value": 1
            }
        ],
        "iconIndex": 79,
        "maxTurns": 2,
        "message1": "は魔法を反射するようになった！",
        "message2": "は魔法を反射するようになった！",
        "message3": "",
        "message4": "",
        "minTurns": 2,
        "motion": 0,
        "name": "魔法反射",
        "note": "",
        "overlay": 0,
        "priority": 50,
        "removeAtBattleEnd": true,
        "removeByDamage": false,
        "removeByRestriction": false,
        "removeByWalking": false,
        "restriction": 0,
        "stepsToRemove": 100
    },
    {
        "id": 30,
        "autoRemovalTiming": 2,
        "chanceByDamage": 100,
        "traits": [
            {
                "code": 22,
                "dataId": 6,
                "value": 1
            }
        ],
        "iconIndex": 79,
        "maxTurns": 1,
        "message1": "は魔法を反射するようになった！",
        "message2": "は魔法を反射するようになった！",
        "message3": "",
        "message4": "",
        "minTurns": 1,
        "motion": 0,
        "name": "物理反射",
        "note": "",
        "overlay": 0,
        "priority": 50,
        "removeAtBattleEnd": true,
        "removeByDamage": false,
        "removeByRestriction": false,
        "removeByWalking": false,
        "restriction": 0,
        "stepsToRemove": 100
    },
    {
        "id": 31,
        "autoRemovalTiming": 0,
        "chanceByDamage": 100,
        "traits": [],
        "iconIndex": 0,
        "maxTurns": 1,
        "message1": "",
        "message2": "",
        "message3": "",
        "message4": "",
        "minTurns": 1,
        "motion": 0,
        "name": "",
        "note": "",
        "overlay": 0,
        "priority": 50,
        "removeAtBattleEnd": false,
        "removeByDamage": false,
        "removeByRestriction": false,
        "removeByWalking": false,
        "restriction": 0,
        "stepsToRemove": 100
    },
    {
        "id": 32,
        "autoRemovalTiming": 2,
        "chanceByDamage": 100,
        "traits": [
            {
                "code": 11,
                "dataId": 2,
                "value": 0
            }
        ],
        "iconIndex": 65,
        "maxTurns": 5,
        "message1": "は水属性の攻撃を遮断した",
        "message2": "は水属性の攻撃を遮断した",
        "message3": "",
        "message4": "",
        "minTurns": 5,
        "motion": 0,
        "name": "水無効",
        "note": "",
        "overlay": 0,
        "priority": 50,
        "removeAtBattleEnd": true,
        "removeByDamage": false,
        "removeByRestriction": false,
        "removeByWalking": false,
        "restriction": 0,
        "stepsToRemove": 100
    },
    {
        "id": 33,
        "autoRemovalTiming": 2,
        "chanceByDamage": 100,
        "traits": [
            {
                "code": 11,
                "dataId": 3,
                "value": 0
            }
        ],
        "iconIndex": 64,
        "maxTurns": 5,
        "message1": "は炎属性の攻撃を遮断した",
        "message2": "は炎属性の攻撃を遮断した",
        "message3": "",
        "message4": "",
        "minTurns": 5,
        "motion": 0,
        "name": "炎無効",
        "note": "",
        "overlay": 0,
        "priority": 50,
        "removeAtBattleEnd": true,
        "removeByDamage": false,
        "removeByRestriction": false,
        "removeByWalking": false,
        "restriction": 0,
        "stepsToRemove": 100
    },
    {
        "id": 34,
        "autoRemovalTiming": 2,
        "chanceByDamage": 100,
        "traits": [
            {
                "code": 11,
                "dataId": 4,
                "value": 0
            }
        ],
        "iconIndex": 66,
        "maxTurns": 5,
        "message1": "は雷属性の攻撃を遮断した",
        "message2": "は雷属性の攻撃を遮断した",
        "message3": "",
        "message4": "",
        "minTurns": 5,
        "motion": 0,
        "name": "雷無効",
        "note": "",
        "overlay": 0,
        "priority": 50,
        "removeAtBattleEnd": true,
        "removeByDamage": false,
        "removeByRestriction": false,
        "removeByWalking": false,
        "restriction": 0,
        "stepsToRemove": 100
    },
    {
        "id": 35,
        "autoRemovalTiming": 2,
        "chanceByDamage": 100,
        "traits": [
            {
                "code": 22,
                "dataId": 1,
                "value": 1
            }
        ],
        "iconIndex": 82,
        "maxTurns": 2,
        "message1": "の回避率が100％になった",
        "message2": "の回避率が100％になった",
        "message3": "",
        "message4": "",
        "minTurns": 2,
        "motion": 0,
        "name": "超回避",
        "note": "",
        "overlay": 0,
        "priority": 50,
        "removeAtBattleEnd": true,
        "removeByDamage": false,
        "removeByRestriction": false,
        "removeByWalking": false,
        "restriction": 0,
        "stepsToRemove": 100
    },
    {
        "id": 36,
        "autoRemovalTiming": 2,
        "chanceByDamage": 100,
        "traits": [
            {
                "code": 62,
                "dataId": 2,
                "value": 1
            }
        ],
        "iconIndex": 75,
        "maxTurns": 1,
        "message1": "は身代わりを繰り出した！",
        "message2": "は身代わりを繰り出した！",
        "message3": "",
        "message4": "の身代わりはなくなった",
        "minTurns": 1,
        "motion": 0,
        "name": "身代わり",
        "note": "",
        "overlay": 0,
        "priority": 50,
        "removeAtBattleEnd": true,
        "removeByDamage": false,
        "removeByRestriction": false,
        "removeByWalking": false,
        "restriction": 0,
        "stepsToRemove": 100
    },
    {
        "id": 37,
        "autoRemovalTiming": 0,
        "chanceByDamage": 100,
        "traits": [],
        "iconIndex": 0,
        "maxTurns": 1,
        "message1": "",
        "message2": "",
        "message3": "",
        "message4": "",
        "minTurns": 1,
        "motion": 0,
        "name": "",
        "note": "",
        "overlay": 0,
        "priority": 50,
        "removeAtBattleEnd": false,
        "removeByDamage": false,
        "removeByRestriction": false,
        "removeByWalking": false,
        "restriction": 0,
        "stepsToRemove": 100
    },
    {
        "id": 38,
        "autoRemovalTiming": 2,
        "chanceByDamage": 100,
        "iconIndex": 9,
        "maxTurns": 2,
        "message1": "は過電圧状態になった！",
        "message2": "は過電圧状態になった！",
        "message3": "",
        "message4": "の過電圧状態がなくなった",
        "minTurns": 2,
        "motion": 0,
        "overlay": 8,
        "name": "過電圧",
        "note": "",
        "priority": 88,
        "releaseByDamage": false,
        "removeAtBattleEnd": true,
        "removeByDamage": false,
        "removeByRestriction": false,
        "removeByWalking": false,
        "restriction": 0,
        "stepsToRemove": 100,
        "traits": [
            {
                "code": 22,
                "dataId": 7,
                "value": -0.1
            }
        ]
    },
    {
        "id": 39,
        "autoRemovalTiming": 2,
        "chanceByDamage": 100,
        "iconIndex": 80,
        "maxTurns": 4,
        "message1": "は覚醒状態になった！",
        "message2": "は覚醒状態になった！",
        "message3": "",
        "message4": "の覚醒状態が終わった！",
        "minTurns": 4,
        "motion": 0,
        "overlay": 0,
        "name": "覚醒",
        "note": "",
        "priority": 88,
        "releaseByDamage": false,
        "removeAtBattleEnd": true,
        "removeByDamage": false,
        "removeByRestriction": false,
        "removeByWalking": false,
        "restriction": 0,
        "stepsToRemove": 100,
        "traits": [
            {
                "code": 22,
                "dataId": 7,
                "value": -0.1
            },
            {
                "code": 21,
                "dataId": 4,
                "value": 1.3
            }
        ]
    },
    {
        "id": 40,
        "autoRemovalTiming": 2,
        "chanceByDamage": 100,
        "iconIndex": 10,
        "maxTurns": 3,
        "message1": "は消えない傷を負った！",
        "message2": "は消えない傷を負った！",
        "message3": "",
        "message4": "の傷が消えた！",
        "minTurns": 3,
        "motion": 0,
        "overlay": 0,
        "name": "傷",
        "note": "",
        "priority": 88,
        "releaseByDamage": false,
        "removeAtBattleEnd": true,
        "removeByDamage": false,
        "removeByRestriction": false,
        "removeByWalking": false,
        "restriction": 0,
        "stepsToRemove": 100,
        "traits": [
            {
                "code": 22,
                "dataId": 7,
                "value": -0.05
            }
        ]
    },
    {
        "id": 41,
        "autoRemovalTiming": 2,
        "chanceByDamage": 100,
        "iconIndex": 79,
        "maxTurns": 4,
        "message1": "の魔力が暴走している！",
        "message2": "の魔力が暴走している！",
        "message3": "",
        "message4": "の魔力の暴走が落ち着いた",
        "minTurns": 3,
        "motion": 0,
        "overlay": 0,
        "name": "魔力暴走",
        "note": "",
        "priority": 88,
        "releaseByDamage": false,
        "removeAtBattleEnd": true,
        "removeByDamage": false,
        "removeByRestriction": false,
        "removeByWalking": false,
        "restriction": 0,
        "stepsToRemove": 100,
        "traits": [
            {
                "code": 22,
                "dataId": 8,
                "value": -0.05
            }
        ]
    },
    {
        "id": 42,
        "autoRemovalTiming": 0,
        "chanceByDamage": 100,
        "iconIndex": 7,
        "maxTurns": 5,
        "message1": "",
        "message2": "",
        "message3": "",
        "message4": "",
        "minTurns": 5,
        "motion": 0,
        "overlay": 0,
        "name": "淫紋",
        "note": "<ASアクター:2>\n<ASスイッチ:23>",
        "priority": 88,
        "releaseByDamage": false,
        "removeAtBattleEnd": false,
        "removeByDamage": false,
        "removeByRestriction": false,
        "removeByWalking": false,
        "restriction": 0,
        "stepsToRemove": 100,
        "traits": [
            {
                "code": 21,
                "dataId": 4,
                "value": 0.9
            },
            {
                "code": 21,
                "dataId": 1,
                "value": 0.95
            }
        ]
    },
    {
        "id": 43,
        "autoRemovalTiming": 0,
        "chanceByDamage": 100,
        "iconIndex": 7,
        "maxTurns": 5,
        "message1": "",
        "message2": "",
        "message3": "",
        "message4": "",
        "minTurns": 5,
        "motion": 0,
        "overlay": 0,
        "name": "ピアスの呪い",
        "note": "<ASアクター:2>\n<ASスイッチ:22>",
        "priority": 88,
        "releaseByDamage": false,
        "removeAtBattleEnd": false,
        "removeByDamage": false,
        "removeByRestriction": false,
        "removeByWalking": false,
        "restriction": 0,
        "stepsToRemove": 100,
        "traits": [
            {
                "code": 21,
                "dataId": 4,
                "value": 0.9
            },
            {
                "code": 21,
                "dataId": 1,
                "value": 0.95
            }
        ]
    },
    {
        "id": 44,
        "autoRemovalTiming": 0,
        "chanceByDamage": 100,
        "iconIndex": 7,
        "maxTurns": 5,
        "message1": "",
        "message2": "",
        "message3": "",
        "message4": "",
        "minTurns": 5,
        "motion": 0,
        "overlay": 0,
        "name": "改造爆乳",
        "note": "<ASアクター:2>\n<ASスイッチ:28>",
        "priority": 88,
        "releaseByDamage": false,
        "removeAtBattleEnd": false,
        "removeByDamage": false,
        "removeByRestriction": false,
        "removeByWalking": false,
        "restriction": 0,
        "stepsToRemove": 100,
        "traits": [
            {
                "code": 21,
                "dataId": 4,
                "value": 0.9
            },
            {
                "code": 21,
                "dataId": 1,
                "value": 0.95
            }
        ]
    },
    {
        "id": 45,
        "autoRemovalTiming": 0,
        "chanceByDamage": 100,
        "iconIndex": 7,
        "maxTurns": 5,
        "message1": "",
        "message2": "",
        "message3": "",
        "message4": "",
        "minTurns": 5,
        "motion": 0,
        "overlay": 0,
        "name": "開発済みまんこ",
        "note": "<ASアクター:2>\n<ASスイッチ:30>",
        "priority": 88,
        "releaseByDamage": false,
        "removeAtBattleEnd": false,
        "removeByDamage": false,
        "removeByRestriction": false,
        "removeByWalking": false,
        "restriction": 0,
        "stepsToRemove": 100,
        "traits": [
            {
                "code": 21,
                "dataId": 4,
                "value": 0.9
            },
            {
                "code": 21,
                "dataId": 1,
                "value": 0.95
            }
        ]
    },
    {
        "id": 46,
        "autoRemovalTiming": 0,
        "chanceByDamage": 100,
        "traits": [],
        "iconIndex": 0,
        "maxTurns": 1,
        "message1": "",
        "message2": "",
        "message3": "",
        "message4": "",
        "minTurns": 1,
        "motion": 0,
        "name": "",
        "note": "",
        "overlay": 0,
        "priority": 50,
        "removeAtBattleEnd": false,
        "removeByDamage": false,
        "removeByRestriction": false,
        "removeByWalking": false,
        "restriction": 0,
        "stepsToRemove": 100
    },
    {
        "id": 47,
        "autoRemovalTiming": 2,
        "chanceByDamage": 100,
        "iconIndex": 11,
        "maxTurns": 5,
        "message1": "はバーサーカー状態になった！",
        "message2": "はバーサーカー状態になった！",
        "message3": "",
        "message4": "のバーサーカー状態は解除された！",
        "minTurns": 5,
        "motion": 0,
        "overlay": 0,
        "name": "バーサーカー",
        "note": "",
        "priority": 88,
        "releaseByDamage": false,
        "removeAtBattleEnd": true,
        "removeByDamage": false,
        "removeByRestriction": false,
        "removeByWalking": false,
        "restriction": 0,
        "stepsToRemove": 100,
        "traits": [
            {
                "code": 21,
                "dataId": 2,
                "value": 2
            },
            {
                "code": 21,
                "dataId": 4,
                "value": 2
            },
            {
                "code": 21,
                "dataId": 3,
                "value": 0.5
            },
            {
                "code": 21,
                "dataId": 5,
                "value": 0.5
            }
        ]
    },
    {
        "id": 48,
        "autoRemovalTiming": 2,
        "chanceByDamage": 100,
        "traits": [
            {
                "code": 11,
                "dataId": 6,
                "value": 0.7
            }
        ],
        "iconIndex": 70,
        "maxTurns": 3,
        "message1": "は光属性の攻撃に耐性を持った！",
        "message2": "は光属性の攻撃に耐性を持った！",
        "message3": "",
        "message4": "",
        "minTurns": 3,
        "motion": 0,
        "name": "光耐性",
        "note": "",
        "overlay": 0,
        "priority": 50,
        "removeAtBattleEnd": true,
        "removeByDamage": false,
        "removeByRestriction": false,
        "removeByWalking": false,
        "restriction": 0,
        "stepsToRemove": 100
    },
    {
        "id": 49,
        "autoRemovalTiming": 2,
        "chanceByDamage": 100,
        "traits": [
            {
                "code": 42,
                "dataId": 1,
                "value": 1
            }
        ],
        "iconIndex": 79,
        "maxTurns": 2,
        "message1": "は魔法を封印された！",
        "message2": "は魔法を封印された！",
        "message3": "",
        "message4": "は魔法が使えるようになった！",
        "minTurns": 1,
        "motion": 0,
        "name": "魔法封印",
        "note": "",
        "overlay": 0,
        "priority": 60,
        "removeAtBattleEnd": true,
        "removeByDamage": false,
        "removeByRestriction": false,
        "removeByWalking": false,
        "restriction": 0,
        "stepsToRemove": 100
    },
    {
        "id": 50,
        "autoRemovalTiming": 2,
        "chanceByDamage": 100,
        "traits": [
            {
                "code": 11,
                "dataId": 6,
                "value": 0.3
            }
        ],
        "iconIndex": 70,
        "maxTurns": 3,
        "message1": "は光属性の攻撃に耐性を持った！",
        "message2": "は光属性の攻撃に耐性を持った！",
        "message3": "",
        "message4": "",
        "minTurns": 3,
        "motion": 0,
        "name": "光耐性　-極-",
        "note": "",
        "overlay": 0,
        "priority": 50,
        "removeAtBattleEnd": true,
        "removeByDamage": false,
        "removeByRestriction": false,
        "removeByWalking": false,
        "restriction": 0,
        "stepsToRemove": 100
    },
    {
        "id": 51,
        "autoRemovalTiming": 2,
        "chanceByDamage": 100,
        "iconIndex": 10,
        "maxTurns": 4,
        "message1": "は謹慎になった。４ターンで気絶してしまう！",
        "message2": "は謹慎になった。４ターンで気絶してしまう！",
        "message3": "",
        "message4": "",
        "minTurns": 4,
        "motion": 0,
        "overlay": 0,
        "name": "謹慎",
        "note": "",
        "priority": 88,
        "releaseByDamage": false,
        "removeAtBattleEnd": true,
        "removeByDamage": false,
        "removeByRestriction": false,
        "removeByWalking": false,
        "restriction": 0,
        "stepsToRemove": 100,
        "traits": [
            {
                "code": 22,
                "dataId": 7,
                "value": -0.3
            }
        ]
    },
    {
        "id": 52,
        "autoRemovalTiming": 0,
        "chanceByDamage": 100,
        "traits": [],
        "iconIndex": 0,
        "maxTurns": 1,
        "message1": "",
        "message2": "",
        "message3": "",
        "message4": "",
        "minTurns": 1,
        "motion": 0,
        "name": "",
        "note": "",
        "overlay": 0,
        "priority": 50,
        "removeAtBattleEnd": false,
        "removeByDamage": false,
        "removeByRestriction": false,
        "removeByWalking": false,
        "restriction": 0,
        "stepsToRemove": 100
    },
    {
        "id": 53,
        "autoRemovalTiming": 0,
        "chanceByDamage": 100,
        "iconIndex": 71,
        "maxTurns": 4,
        "message1": "は深淵状態になった",
        "message2": "は深淵状態になった",
        "message3": "",
        "message4": "の深淵状態が解除された",
        "minTurns": 4,
        "motion": 0,
        "overlay": 0,
        "name": "深淵状態",
        "note": "",
        "priority": 88,
        "releaseByDamage": false,
        "removeAtBattleEnd": true,
        "removeByDamage": false,
        "removeByRestriction": false,
        "removeByWalking": false,
        "restriction": 0,
        "stepsToRemove": 100,
        "traits": [
            {
                "code": 21,
                "dataId": 2,
                "value": 1.3
            },
            {
                "code": 21,
                "dataId": 4,
                "value": 1.3
            }
        ]
    },
    {
        "id": 54,
        "autoRemovalTiming": 0,
        "chanceByDamage": 100,
        "traits": [],
        "iconIndex": 0,
        "maxTurns": 1,
        "message1": "",
        "message2": "",
        "message3": "",
        "message4": "",
        "minTurns": 1,
        "motion": 0,
        "name": "",
        "note": "",
        "overlay": 0,
        "priority": 50,
        "removeAtBattleEnd": false,
        "removeByDamage": false,
        "removeByRestriction": false,
        "removeByWalking": false,
        "restriction": 0,
        "stepsToRemove": 100
    },
    {
        "id": 55,
        "autoRemovalTiming": 0,
        "chanceByDamage": 100,
        "iconIndex": 7,
        "maxTurns": 5,
        "message1": "",
        "message2": "",
        "message3": "",
        "message4": "",
        "minTurns": 5,
        "motion": 0,
        "overlay": 0,
        "name": "フェラ狂い",
        "note": "<ASアクター:2>\n<ASスイッチ:299>",
        "priority": 88,
        "releaseByDamage": false,
        "removeAtBattleEnd": false,
        "removeByDamage": false,
        "removeByRestriction": false,
        "removeByWalking": false,
        "restriction": 0,
        "stepsToRemove": 100,
        "traits": [
            {
                "code": 21,
                "dataId": 4,
                "value": 0.95
            }
        ]
    },
    {
        "id": 56,
        "autoRemovalTiming": 0,
        "chanceByDamage": 100,
        "iconIndex": 7,
        "maxTurns": 5,
        "message1": "",
        "message2": "",
        "message3": "",
        "message4": "",
        "minTurns": 5,
        "motion": 0,
        "overlay": 0,
        "name": "ザコ乳首",
        "note": "<ASアクター:2>\n<ASスイッチ:300>",
        "priority": 88,
        "releaseByDamage": false,
        "removeAtBattleEnd": false,
        "removeByDamage": false,
        "removeByRestriction": false,
        "removeByWalking": false,
        "restriction": 0,
        "stepsToRemove": 100,
        "traits": [
            {
                "code": 21,
                "dataId": 4,
                "value": 0.95
            }
        ]
    },
    {
        "id": 57,
        "autoRemovalTiming": 0,
        "chanceByDamage": 100,
        "iconIndex": 7,
        "maxTurns": 5,
        "message1": "",
        "message2": "",
        "message3": "",
        "message4": "",
        "minTurns": 5,
        "motion": 0,
        "overlay": 0,
        "name": "ザコマンコ",
        "note": "<ASアクター:2>\n<ASスイッチ:301>",
        "priority": 88,
        "releaseByDamage": false,
        "removeAtBattleEnd": false,
        "removeByDamage": false,
        "removeByRestriction": false,
        "removeByWalking": false,
        "restriction": 0,
        "stepsToRemove": 100,
        "traits": [
            {
                "code": 21,
                "dataId": 4,
                "value": 0.95
            }
        ]
    },
    {
        "id": 58,
        "autoRemovalTiming": 0,
        "chanceByDamage": 100,
        "iconIndex": 7,
        "maxTurns": 5,
        "message1": "",
        "message2": "",
        "message3": "",
        "message4": "",
        "minTurns": 5,
        "motion": 0,
        "overlay": 0,
        "name": "開発済みアナル",
        "note": "<ASアクター:2>\n<ASスイッチ:302>",
        "priority": 88,
        "releaseByDamage": false,
        "removeAtBattleEnd": false,
        "removeByDamage": false,
        "removeByRestriction": false,
        "removeByWalking": false,
        "restriction": 0,
        "stepsToRemove": 100,
        "traits": [
            {
                "code": 21,
                "dataId": 4,
                "value": 0.95
            }
        ]
    },
    {
        "id": 59,
        "autoRemovalTiming": 0,
        "chanceByDamage": 100,
        "iconIndex": 7,
        "maxTurns": 5,
        "message1": "",
        "message2": "",
        "message3": "",
        "message4": "",
        "minTurns": 5,
        "motion": 0,
        "overlay": 0,
        "name": "ドスケベ女",
        "note": "<ASアクター:2>\n<ASスイッチ:303>",
        "priority": 88,
        "releaseByDamage": false,
        "removeAtBattleEnd": false,
        "removeByDamage": false,
        "removeByRestriction": false,
        "removeByWalking": false,
        "restriction": 0,
        "stepsToRemove": 100,
        "traits": [
            {
                "code": 21,
                "dataId": 4,
                "value": 0.95
            }
        ]
    },
    {
        "id": 60,
        "autoRemovalTiming": 0,
        "chanceByDamage": 100,
        "traits": [],
        "iconIndex": 0,
        "maxTurns": 1,
        "message1": "",
        "message2": "",
        "message3": "",
        "message4": "",
        "minTurns": 1,
        "motion": 0,
        "name": "",
        "note": "",
        "overlay": 0,
        "priority": 50,
        "removeAtBattleEnd": false,
        "removeByDamage": false,
        "removeByRestriction": false,
        "removeByWalking": false,
        "restriction": 0,
        "stepsToRemove": 100
    }
]